Metadata-Version: 2.1
Name: aray
Version: 0.0.1.post1560579215
Summary: Public personal python package
Home-page: https://github.com/machinaut/aray
Author: A Ray
Author-email: a@machinaut.com
License: UNKNOWN
Platform: UNKNOWN
Classifier: Programming Language :: Python :: 3
Classifier: Operating System :: OS Independent
